INSTALLATION.txt
LICENSE.txt
MANIFEST.in
README.rst
make_version.py
makefile
pyproject.toml
setup.cfg
setup.py
src/qcdevol/__init__.py
src/qcdevol/_version.py
src/qcdevol/qcdevol.py
src/qcdevol.egg-info/PKG-INFO
src/qcdevol.egg-info/SOURCES.txt
src/qcdevol.egg-info/dependency_links.txt
src/qcdevol.egg-info/not-zip-safe
src/qcdevol.egg-info/requires.txt
src/qcdevol.egg-info/top_level.txt
tests/test_qcdevol.py