Metadata-Version: 2.1
Name: qcdevol
Version: 4.1
Summary: Evolution of QCD couplings, masses and other renormalization parameters.
Home-page: https://github.com/gplepage/qcdevol
Author: G. Peter Lepage
Author-email: g.p.lepage@cornell.edu
License: GPLv3
Requires-Python: >=3.6
License-File: LICENSE.txt
Requires-Dist: numpy
Requires-Dist: gvar
